pygic/__init__.py
pygic/cli.py
pygic/config.py
pygic/file.py
pygic/gitignore.py
pygic/utils.py
pygic/templates/1C-Bitrix.gitignore
pygic/templates/1C.gitignore
pygic/templates/A-Frame.gitignore
pygic/templates/AL.gitignore
pygic/templates/ASPNETCore.gitignore
pygic/templates/ATE.gitignore
pygic/templates/ATS.gitignore
pygic/templates/AWR.gitignore
pygic/templates/Actionscript.gitignore
pygic/templates/Ada.gitignore
pygic/templates/Adobe.gitignore
pygic/templates/AdvancedInstaller.gitignore
pygic/templates/AdventureGameStudio.gitignore
pygic/templates/Agda.gitignore
pygic/templates/AlteraQuartusII.gitignore
pygic/templates/Altium.gitignore
pygic/templates/Amplify.gitignore
pygic/templates/Android+reports.patch
pygic/templates/Android.gitignore
pygic/templates/Android.patch
pygic/templates/AndroidStudio.gitignore
pygic/templates/AndroidStudio.patch
pygic/templates/Angular.gitignore
pygic/templates/Anjuta.gitignore
pygic/templates/Ansible.gitignore
pygic/templates/AnsibleTower.gitignore
pygic/templates/ApacheCordova.gitignore
pygic/templates/ApacheHadoop.gitignore
pygic/templates/AppBuilder.gitignore
pygic/templates/AppCode+all.gitignore
pygic/templates/AppCode+all.patch
pygic/templates/AppCode+iml.gitignore
pygic/templates/AppCode+iml.patch
pygic/templates/AppCode.gitignore
pygic/templates/AppCode.patch
pygic/templates/AppEngine.gitignore
pygic/templates/AppceleratorTitanium.gitignore
pygic/templates/AptanaStudio.gitignore
pygic/templates/Arcanist.gitignore
pygic/templates/ArchLinuxPackages.gitignore
pygic/templates/Archive.gitignore
pygic/templates/Archives.gitignore
pygic/templates/Assembler.gitignore
pygic/templates/Astro.gitignore
pygic/templates/AtmelStudio.gitignore
pygic/templates/Audio.gitignore
pygic/templates/Autohotkey.gitignore
pygic/templates/AutomationStudio.gitignore
pygic/templates/Autotools+strict.gitignore
pygic/templates/Autotools+strict.patch
pygic/templates/Autotools.gitignore
pygic/templates/Autotools.patch
pygic-1.0.0.dist-info/METADATA
pygic-1.0.0.dist-info/WHEEL
pygic-1.0.0.dist-info/entry_points.txt
pygic-1.0.0.dist-info/licenses/LICENSE
pygic-1.0.0.dist-info/RECORD
