Metadata-Version: 2.4
Name: pygic
Version: 1.0.0
Summary: A command line tool for generating .gitignore files.
Author: Loris Floquet
License: MIT License
License-File: LICENSE
Requires-Python: >=3.10
Requires-Dist: click>=8.1.7
Requires-Dist: rich-click>=1.8.8
Requires-Dist: termcolor>=2.3.0
Provides-Extra: all
Requires-Dist: appdirs>=1.4.4; extra == 'all'
Requires-Dist: dulwich>=0.22.6; extra == 'all'
Requires-Dist: gitpython>=3.1.43; extra == 'all'
Requires-Dist: pzp>=0.0.24; extra == 'all'
Requires-Dist: yaspin>=3.1.0; extra == 'all'
Provides-Extra: dulwich
Requires-Dist: appdirs>=1.4.4; extra == 'dulwich'
Requires-Dist: dulwich>=0.22.6; extra == 'dulwich'
Requires-Dist: yaspin>=3.1.0; extra == 'dulwich'
Provides-Extra: git
Requires-Dist: appdirs>=1.4.4; extra == 'git'
Requires-Dist: gitpython>=3.1.43; extra == 'git'
Requires-Dist: yaspin>=3.1.0; extra == 'git'
Provides-Extra: search
Requires-Dist: pzp>=0.0.24; extra == 'search'
